{"stats":{"minecraft:picked_up":{"enhancing:enchanting_cursed_rune":44,"minecraft:wheat_seeds":3,"minecraft:torch":1,"enhancing:enchanting_rune":56,"minecraft:dirt":16,"minecraft:cobblestone":1},"minecraft:used":{"enhancing:mystical_crossbow":64,"minecraft:firework_rocket":111,"minecraft:anvil":3,"minecraft:crossbow":7,"minecraft:ender_pearl":5,"minecraft:iron_boots":1},"minecraft:dropped":{"enhancing:enchanting_rune":19,"minecraft:firework_rocket":66},"minecraft:killed":{"minecraft:pig":3},"minecraft:custom":{"minecraft:time_since_rest":41875,"minecraft:open_chest":1,"minecraft:sprint_one_cm":10674,"minecraft:play_time":41875,"minecraft:walk_one_cm":43004,"minecraft:mob_kills":4,"minecraft:sneak_time":476,"minecraft:walk_under_water_one_cm":69969,"minecraft:interact_with_anvil":7,"minecraft:drop":22,"minecraft:aviate_one_cm":2572127,"minecraft:jump":190,"minecraft:damage_dealt":60,"minecraft:leave_game":4,"minecraft:walk_on_water_one_cm":6008,"minecraft:time_since_death":41875,"minecraft:total_world_time":47334,"minecraft:swim_one_cm":3444,"minecraft:fly_one_cm":113078}},"DataVersion":3120}